MANIFEST.in
README.md
setup.py
imgs/icon.png
pycomon/__init__.py
pycomon/gui.py
pycomon/tester.py
pycomon.egg-info/PKG-INFO
pycomon.egg-info/SOURCES.txt
pycomon.egg-info/dependency_links.txt
pycomon.egg-info/entry_points.txt
pycomon.egg-info/top_level.txt