Metadata-Version: 1.1
Name: pycomon
Version: 1.1.1
Summary: A simple connection monitor
Home-page: https://github.com/wuerges/connection_monitor
Author: Emilio Wuerges
Author-email: wuerges@gmail.com
License: BSD
Keywords: conection monitor
Platform: UNKNOWN
Classifier: Development Status :: 3 - Alpha
Classifier: Intended Audience :: End Users/Desktop
Classifier: Topic :: System :: Networking :: Monitoring
Classifier: License :: OSI Approved :: BSD License
Classifier: Programming Language :: Python :: 3
Classifier: Programming Language :: Python :: 3.2
Classifier: Programming Language :: Python :: 3.3
Classifier: Programming Language :: Python :: 3.4
Classifier: Programming Language :: Python :: 3.5
